[
  {
    "goods_no": "1108298022",
    "rank": 1,
    "image_url": "https://gd.image-qoo10.jp/li/950/418/8377418950.g_300-w-st_g.jpg",
    "title": "【大容量】【BEST】アルファアルブチン2ニキビ跡ケアセラム(50mL) / Qoo10月間コスメ1位(25年12月美容液部門) /トラネキサム酸 ナイアシン ザRX",
    "brand": "COSRX",
    "price_jpy": 2356,
    "item_url": "https://m.qoo10.jp/gmkt.inc/Mobile/Goods/goods.aspx?goodscode=1108298022"
  },
  {
    "goods_no": "617326490",
    "rank": 2,
    "image_url": "https://gd.image-qoo10.jp/li/462/420/8377420462.g_300-w-st_g.jpg",
    "title": "【リニュアル】【NOニオイ】ザ・ビタミンC23セラム 2世代(20g) / 生ビタミンC / 純粋ビタミンC / 透明感のある肌 / 無香料 / RX / 美容液",
    "brand": "COSRX",
    "price_jpy": 2546,
    "item_url": "https://m.qoo10.jp/gmkt.inc/Mobile/Goods/goods.aspx?goodscode=617326490"
  },
  {
    "goods_no": "1196385786",
    "rank": 3,
    "image_url": "https://gd.image-qoo10.jp/li/124/416/8377416124.g_300-w-st_g.jpg",
    "title": "【5月新作/Qoo10先行発売】ザ・ブルーペプチド バクチオール 縦毛穴 セラム 50mL/コッパーペプチド/毛穴タイトニング/縦毛穴/たるみ/化粧ノリ/キメ/ハリ/敏感肌/エイジングケア/透明感",
    "brand": "COSRX",
    "price_jpy": 3040,
    "item_url": "https://m.qoo10.jp/gmkt.inc/Mobile/Goods/goods.aspx?goodscode=1196385786"
  },
  {
    "goods_no": "1149713621",
    "rank": 4,
    "image_url": "https://gd.image-qoo10.jp/li/981/421/8377421981.g_300-w-st_g.jpg",
    "title": "【神保湿】セラミド肌バリア保湿クリーム 80mL / 赤ちゃんも使える優しいフェイスクリーム / 肌バリアケア／うるツヤ肌 / モイスチャライザー / スキン ザ RX",
    "brand": "COSRX",
    "price_jpy": 2612,
    "item_url": "https://m.qoo10.jp/gmkt.inc/Mobile/Goods/goods.aspx?goodscode=1149713621"
  },
  {
    "goods_no": "1018520726",
    "rank": 5,
    "image_url": "https://gd.image-qoo10.jp/li/747/422/8377422747.g_300-w-st_g.jpg",
    "title": "【大容量】ザ・6ペプチドスキンブースターセラム(150mL) / 導入美容液 / 先行美容液 / 化粧水 / 6種機能性ペプチドで様々な肌悩み解決 / RX",
    "brand": "COSRX",
    "price_jpy": 2356,
    "item_url": "https://m.qoo10.jp/gmkt.inc/Mobile/Goods/goods.aspx?goodscode=1018520726"
  }
]